evops/__init__.py
evops/benchmark/__init__.py
evops/benchmark/association.py
evops/benchmark/default.py
evops/benchmark/detailed.py
evops/benchmark/dice.py
evops/benchmark/iou.py
evops/benchmark/mean.py
evops/benchmark/panoptic.py
evops/metrics/__init__.py
evops/metrics/association.py
evops/metrics/constants.py
evops/metrics/full_statistics.py
evops/metrics/instance_based.py
evops/metrics/point_based.py
evops/utils/__init__.py
evops/utils/association_utils.py
evops/utils/check_input.py
evops/utils/iou_overlap.py
evops/utils/metrics_utils.py
evops-1.0.0.dist-info/LICENSE
evops-1.0.0.dist-info/WHEEL
evops-1.0.0.dist-info/METADATA
evops-1.0.0.dist-info/RECORD
