Metadata-Version: 2.1
Name: evops
Version: 1.0.0
Summary: Evaluation of Plane Segmentation.
Home-page: https://evops.netlify.app/
License: APACHE
Author: Pavel Mokeev
Requires-Python: >=3.7.1,<4.0.0
Classifier: License :: Other/Proprietary License
Classifier: Programming Language :: Python :: 3
Classifier: Programming Language :: Python :: 3.10
Classifier: Programming Language :: Python :: 3.8
Classifier: Programming Language :: Python :: 3.9
Requires-Dist: importlib-metadata (>=4.8.3,<5.0.0)
Requires-Dist: importlib-resources (>=5.7.1,<6.0.0)
Requires-Dist: nptyping (>=1.4.4,<2.0.0)
Requires-Dist: numpy (>=1.19.0,<2.0.0)
Project-URL: Repository, https://github.com/MobileRoboticsSkoltech/evops
